ezmail/__init__.py
ezmail/ezmail.py
ezmail/ezreader.py
ezmail/ezsender.py
ezmail/utils.py
py_ezmail-2.3.5.dist-info/licenses/LICENSE
py_ezmail-2.3.5.dist-info/METADATA
py_ezmail-2.3.5.dist-info/WHEEL
py_ezmail-2.3.5.dist-info/top_level.txt
py_ezmail-2.3.5.dist-info/RECORD
