Metadata-Version: 2.4
Name: py-ezmail
Version: 2.3.5
Summary: Send and read emails easily — with attachments, inline images, IMAP management, and OAuth2 authentication.
Author-email: Luiz Henrique Brunca <luizhenriquebrunca@gmail.com>
License: MIT
Project-URL: Homepage, https://github.com/luizbrunca/ezmail
Project-URL: Repository, https://github.com/luizbrunca/ezmail
Project-URL: Issues, https://github.com/luizbrunca/ezmail/issues
Project-URL: Documentation, https://github.com/luizbrunca/ezmail#readme
Keywords: email,smtp,imap,html,oauth2,automation,brunca,ezmail,attachments
Classifier: Development Status :: 5 - Production/Stable
Classifier: Intended Audience :: Developers
Classifier: Programming Language :: Python :: 3
Classifier: Programming Language :: Python :: 3.8
Classifier: Programming Language :: Python :: 3.12
Classifier: Topic :: Communications :: Email
Classifier: Topic :: Software Development :: Libraries :: Python Modules
Classifier: Operating System :: OS Independent
Requires-Python: >=3.8
License-File: LICENSE
Requires-Dist: jinja2>=3.0.0
Dynamic: license-file
